rtl/fastserial/clock_fastserial.v

module clock_fastserial(input wire i_clk, 
                        output wire o_fsclk)
                       ;
parameter fast_serial_divider = 4;                     

reg [15:0] counter;
initial begin
    counter = 0;
end

always @(posedge i_clk) begin
  
    counter <= counter + 1'b1;
    if (counter >=  (fast_serial_divider -1)) begin
            counter <= 0;
    end
end	 



assign o_fsclk = (counter < ((fast_serial_divider/2)))?1'b0: 1'b1;


endmodule
//eof

tb/fast_serial_timer_tb.v
`default_nettype none
`timescale 1 ns/10 ps  // time-unit = 1 us, precision = 10 ps

module fast_serial_timer_tb;

    reg clk=0;
    wire o_fsclk;
    wire o_negdge_fsclk;
    reg [4:0]state = 0;
    reg wait_clk=0;

    clock_fastserial UUT( .i_clk(clk),
                    .o_fsclk(o_fsclk));
                    
                 
    always begin
        #1 clk =!clk;
    end

initial begin
    $dumpfile("fast_serial_timer_tb.vcd");
    $dumpvars(0,fast_serial_timer_tb);

    #500;

    


    #10 $finish;
end

always @(posedge clk) begin
        if (~o_fsclk && wait_clk)
            wait_clk <=0;
end
always @(posedge clk) begin

    if (o_fsclk && ~wait_clk) begin
        case (state)
        0: state <= state+ 1;
        1: state <= state+ 1;
        2: state <= state+ 1;
        3: state <= state+ 1;
        4: state <= state+ 1;
        default:
            state <= 0;
        endcase
        wait_clk <= 1;
    
    end	 
end




endmodule

tb/fast_serial_timer_tb.vcd
$date
	Wed May 20 14:55:45 2020
$end
$version
	Icarus Verilog
$end
$timescale
	10ps
$end
$scope module fast_serial_timer_tb $end
$var wire 1 ! o_fsclk $end
$var reg 1 " clk $end
$var reg 5 # state [4:0] $end
$var reg 1 $ wait_clk $end
$scope module UUT $end
$var wire 1 " i_clk $end
$var wire 1 ! o_fsclk $end
$var reg 16 % counter [15:0] $end
$upscope $end
$upscope $end
$enddefinitions $end
#0
$dumpvars
b0 %
0$
b0 #
0"
0!
$end
#100
b1 %
1"
#200
0"
#300
1!
b10 %
1"
#400
0"
#500
b11 %
1$
b1 #
1"
#600
0"
#700
0!
b0 %
1"
#800
0"
#900
b1 %
0$
1"
#1000
0"
#1100
1!
b10 %
1"
#1200
0"
#1300
b11 %
1$
b10 #
1"
#1400
0"
#1500
0!
b0 %
1"
#1600
0"
#1700
b1 %
0$
1"
#1800
0"
#1900
1!
b10 %
1"
#2000
0"
#2100
b11 %
1$
b11 #
1"
#2200
0"
#2300
0!
b0 %
1"
#2400
0"
#2500
b1 %
0$
1"
#2600
0"
#2700
1!
b10 %
1"
#2800
0"
#2900
b11 %
1$
b100 #
1"
#3000
0"
#3100
0!
b0 %
1"
#3200
0"
#3300
b1 %
0$
1"
#3400
0"
#3500
1!
b10 %
1"
#3600
0"
#3700
b11 %
1$
b101 #
1"
#3800
0"
#3900
0!
b0 %
1"
#4000
0"
#4100
b1 %
0$
1"
#4200
0"
#4300
1!
b10 %
1"
#4400
0"
#4500
b11 %
1$
b0 #
1"
#4600
0"
#4700
0!
b0 %
1"
#4800
0"
#4900
b1 %
0$
1"
#5000
0"
#5100
1!
b10 %
1"
#5200
0"
#5300
b11 %
1$
b1 #
1"
#5400
0"
#5500
0!
b0 %
1"
#5600
0"
#5700
b1 %
0$
1"
#5800
0"
#5900
1!
b10 %
1"
#6000
0"
#6100
b11 %
1$
b10 #
1"
#6200
0"
#6300
0!
b0 %
1"
#6400
0"
#6500
b1 %
0$
1"
#6600
0"
#6700
1!
b10 %
1"
#6800
0"
#6900
b11 %
1$
b11 #
1"
#7000
0"
#7100
0!
b0 %
1"
#7200
0"
#7300
b1 %
0$
1"
#7400
0"
#7500
1!
b10 %
1"
#7600
0"
#7700
b11 %
1$
b100 #
1"
#7800
0"
#7900
0!
b0 %
1"
#8000
0"
#8100
b1 %
0$
1"
#8200
0"
#8300
1!
b10 %
1"
#8400
0"
#8500
b11 %
1$
b101 #
1"
#8600
0"
#8700
0!
b0 %
1"
#8800
0"
#8900
b1 %
0$
1"
#9000
0"
#9100
1!
b10 %
1"
#9200
0"
#9300
b11 %
1$
b0 #
1"
#9400
0"
#9500
0!
b0 %
1"
#9600
0"
#9700
b1 %
0$
1"
#9800
0"
#9900
1!
b10 %
1"
#10000
0"
#10100
b11 %
1$
b1 #
1"
#10200
0"
#10300
0!
b0 %
1"
#10400
0"
#10500
b1 %
0$
1"
#10600
0"
#10700
1!
b10 %
1"
#10800
0"
#10900
b11 %
1$
b10 #
1"
#11000
0"
#11100
0!
b0 %
1"
#11200
0"
#11300
b1 %
0$
1"
#11400
0"
#11500
1!
b10 %
1"
#11600
0"
#11700
b11 %
1$
b11 #
1"
#11800
0"
#11900
0!
b0 %
1"
#12000
0"
#12100
b1 %
0$
1"
#12200
0"
#12300
1!
b10 %
1"
#12400
0"
#12500
b11 %
1$
b100 #
1"
#12600
0"
#12700
0!
b0 %
1"
#12800
0"
#12900
b1 %
0$
1"
#13000
0"
#13100
1!
b10 %
1"
#13200
0"
#13300
b11 %
1$
b101 #
1"
#13400
0"
#13500
0!
b0 %
1"
#13600
0"
#13700
b1 %
0$
1"
#13800
0"
#13900
1!
b10 %
1"
#14000
0"
#14100
b11 %
1$
b0 #
1"
#14200
0"
#14300
0!
b0 %
1"
#14400
0"
#14500
b1 %
0$
1"
#14600
0"
#14700
1!
b10 %
1"
#14800
0"
#14900
b11 %
1$
b1 #
1"
#15000
0"
#15100
0!
b0 %
1"
#15200
0"
#15300
b1 %
0$
1"
#15400
0"
#15500
1!
b10 %
1"
#15600
0"
#15700
b11 %
1$
b10 #
1"
#15800
0"
#15900
0!
b0 %
1"
#16000
0"
#16100
b1 %
0$
1"
#16200
0"
#16300
1!
b10 %
1"
#16400
0"
#16500
b11 %
1$
b11 #
1"
#16600
0"
#16700
0!
b0 %
1"
#16800
0"
#16900
b1 %
0$
1"
#17000
0"
#17100
1!
b10 %
1"
#17200
0"
#17300
b11 %
1$
b100 #
1"
#17400
0"
#17500
0!
b0 %
1"
#17600
0"
#17700
b1 %
0$
1"
#17800
0"
#17900
1!
b10 %
1"
#18000
0"
#18100
b11 %
1$
b101 #
1"
#18200
0"
#18300
0!
b0 %
1"
#18400
0"
#18500
b1 %
0$
1"
#18600
0"
#18700
1!
b10 %
1"
#18800
0"
#18900
b11 %
1$
b0 #
1"
#19000
0"
#19100
0!
b0 %
1"
#19200
0"
#19300
b1 %
0$
1"
#19400
0"
#19500
1!
b10 %
1"
#19600
0"
#19700
b11 %
1$
b1 #
1"
#19800
0"
#19900
0!
b0 %
1"
#20000
0"
#20100
b1 %
0$
1"
#20200
0"
#20300
1!
b10 %
1"
#20400
0"
#20500
b11 %
1$
b10 #
1"
#20600
0"
#20700
0!
b0 %
1"
#20800
0"
#20900
b1 %
0$
1"
#21000
0"
#21100
1!
b10 %
1"
#21200
0"
#21300
b11 %
1$
b11 #
1"
#21400
0"
#21500
0!
b0 %
1"
#21600
0"
#21700
b1 %
0$
1"
#21800
0"
#21900
1!
b10 %
1"
#22000
0"
#22100
b11 %
1$
b100 #
1"
#22200
0"
#22300
0!
b0 %
1"
#22400
0"
#22500
b1 %
0$
1"
#22600
0"
#22700
1!
b10 %
1"
#22800
0"
#22900
b11 %
1$
b101 #
1"
#23000
0"
#23100
0!
b0 %
1"
#23200
0"
#23300
b1 %
0$
1"
#23400
0"
#23500
1!
b10 %
1"
#23600
0"
#23700
b11 %
1$
b0 #
1"
#23800
0"
#23900
0!
b0 %
1"
#24000
0"
#24100
b1 %
0$
1"
#24200
0"
#24300
1!
b10 %
1"
#24400
0"
#24500
b11 %
1$
b1 #
1"
#24600
0"
#24700
0!
b0 %
1"
#24800
0"
#24900
b1 %
0$
1"
#25000
0"
#25100
1!
b10 %
1"
#25200
0"
#25300
b11 %
1$
b10 #
1"
#25400
0"
#25500
0!
b0 %
1"
#25600
0"
#25700
b1 %
0$
1"
#25800
0"
#25900
1!
b10 %
1"
#26000
0"
#26100
b11 %
1$
b11 #
1"
#26200
0"
#26300
0!
b0 %
1"
#26400
0"
#26500
b1 %
0$
1"
#26600
0"
#26700
1!
b10 %
1"
#26800
0"
#26900
b11 %
1$
b100 #
1"
#27000
0"
#27100
0!
b0 %
1"
#27200
0"
#27300
b1 %
0$
1"
#27400
0"
#27500
1!
b10 %
1"
#27600
0"
#27700
b11 %
1$
b101 #
1"
#27800
0"
#27900
0!
b0 %
1"
#28000
0"
#28100
b1 %
0$
1"
#28200
0"
#28300
1!
b10 %
1"
#28400
0"
#28500
b11 %
1$
b0 #
1"
#28600
0"
#28700
0!
b0 %
1"
#28800
0"
#28900
b1 %
0$
1"
#29000
0"
#29100
1!
b10 %
1"
#29200
0"
#29300
b11 %
1$
b1 #
1"
#29400
0"
#29500
0!
b0 %
1"
#29600
0"
#29700
b1 %
0$
1"
#29800
0"
#29900
1!
b10 %
1"
#30000
0"
#30100
b11 %
1$
b10 #
1"
#30200
0"
#30300
0!
b0 %
1"
#30400
0"
#30500
b1 %
0$
1"
#30600
0"
#30700
1!
b10 %
1"
#30800
0"
#30900
b11 %
1$
b11 #
1"
#31000
0"
#31100
0!
b0 %
1"
#31200
0"
#31300
b1 %
0$
1"
#31400
0"
#31500
1!
b10 %
1"
#31600
0"
#31700
b11 %
1$
b100 #
1"
#31800
0"
#31900
0!
b0 %
1"
#32000
0"
#32100
b1 %
0$
1"
#32200
0"
#32300
1!
b10 %
1"
#32400
0"
#32500
b11 %
1$
b101 #
1"
#32600
0"
#32700
0!
b0 %
1"
#32800
0"
#32900
b1 %
0$
1"
#33000
0"
#33100
1!
b10 %
1"
#33200
0"
#33300
b11 %
1$
b0 #
1"
#33400
0"
#33500
0!
b0 %
1"
#33600
0"
#33700
b1 %
0$
1"
#33800
0"
#33900
1!
b10 %
1"
#34000
0"
#34100
b11 %
1$
b1 #
1"
#34200
0"
#34300
0!
b0 %
1"
#34400
0"
#34500
b1 %
0$
1"
#34600
0"
#34700
1!
b10 %
1"
#34800
0"
#34900
b11 %
1$
b10 #
1"
#35000
0"
#35100
0!
b0 %
1"
#35200
0"
#35300
b1 %
0$
1"
#35400
0"
#35500
1!
b10 %
1"
#35600
0"
#35700
b11 %
1$
b11 #
1"
#35800
0"
#35900
0!
b0 %
1"
#36000
0"
#36100
b1 %
0$
1"
#36200
0"
#36300
1!
b10 %
1"
#36400
0"
#36500
b11 %
1$
b100 #
1"
#36600
0"
#36700
0!
b0 %
1"
#36800
0"
#36900
b1 %
0$
1"
#37000
0"
#37100
1!
b10 %
1"
#37200
0"
#37300
b11 %
1$
b101 #
1"
#37400
0"
#37500
0!
b0 %
1"
#37600
0"
#37700
b1 %
0$
1"
#37800
0"
#37900
1!
b10 %
1"
#38000
0"
#38100
b11 %
1$
b0 #
1"
#38200
0"
#38300
0!
b0 %
1"
#38400
0"
#38500
b1 %
0$
1"
#38600
0"
#38700
1!
b10 %
1"
#38800
0"
#38900
b11 %
1$
b1 #
1"
#39000
0"
#39100
0!
b0 %
1"
#39200
0"
#39300
b1 %
0$
1"
#39400
0"
#39500
1!
b10 %
1"
#39600
0"
#39700
b11 %
1$
b10 #
1"
#39800
0"
#39900
0!
b0 %
1"
#40000
0"
#40100
b1 %
0$
1"
#40200
0"
#40300
1!
b10 %
1"
#40400
0"
#40500
b11 %
1$
b11 #
1"
#40600
0"
#40700
0!
b0 %
1"
#40800
0"
#40900
b1 %
0$
1"
#41000
0"
#41100
1!
b10 %
1"
#41200
0"
#41300
b11 %
1$
b100 #
1"
#41400
0"
#41500
0!
b0 %
1"
#41600
0"
#41700
b1 %
0$
1"
#41800
0"
#41900
1!
b10 %
1"
#42000
0"
#42100
b11 %
1$
b101 #
1"
#42200
0"
#42300
0!
b0 %
1"
#42400
0"
#42500
b1 %
0$
1"
#42600
0"
#42700
1!
b10 %
1"
#42800
0"
#42900
b11 %
1$
b0 #
1"
#43000
0"
#43100
0!
b0 %
1"
#43200
0"
#43300
b1 %
0$
1"
#43400
0"
#43500
1!
b10 %
1"
#43600
0"
#43700
b11 %
1$
b1 #
1"
#43800
0"
#43900
0!
b0 %
1"
#44000
0"
#44100
b1 %
0$
1"
#44200
0"
#44300
1!
b10 %
1"
#44400
0"
#44500
b11 %
1$
b10 #
1"
#44600
0"
#44700
0!
b0 %
1"
#44800
0"
#44900
b1 %
0$
1"
#45000
0"
#45100
1!
b10 %
1"
#45200
0"
#45300
b11 %
1$
b11 #
1"
#45400
0"
#45500
0!
b0 %
1"
#45600
0"
#45700
b1 %
0$
1"
#45800
0"
#45900
1!
b10 %
1"
#46000
0"
#46100
b11 %
1$
b100 #
1"
#46200
0"
#46300
0!
b0 %
1"
#46400
0"
#46500
b1 %
0$
1"
#46600
0"
#46700
1!
b10 %
1"
#46800
0"
#46900
b11 %
1$
b101 #
1"
#47000
0"
#47100
0!
b0 %
1"
#47200
0"
#47300
b1 %
0$
1"
#47400
0"
#47500
1!
b10 %
1"
#47600
0"
#47700
b11 %
1$
b0 #
1"
#47800
0"
#47900
0!
b0 %
1"
#48000
0"
#48100
b1 %
0$
1"
#48200
0"
#48300
1!
b10 %
1"
#48400
0"
#48500
b11 %
1$
b1 #
1"
#48600
0"
#48700
0!
b0 %
1"
#48800
0"
#48900
b1 %
0$
1"
#49000
0"
#49100
1!
b10 %
1"
#49200
0"
#49300
b11 %
1$
b10 #
1"
#49400
0"
#49500
0!
b0 %
1"
#49600
0"
#49700
b1 %
0$
1"
#49800
0"
#49900
1!
b10 %
1"
#50000
0"
#50100
b11 %
1$
b11 #
1"
#50200
0"
#50300
0!
b0 %
1"
#50400
0"
#50500
b1 %
0$
1"
#50600
0"
#50700
1!
b10 %
1"
#50800
0"
#50900
b11 %
1$
b100 #
1"
